Metadata-Version: 2.1
Name: test-pypi-install-package
Version: 0.0.1
Summary: test pypi package
Home-page: https://code.alipay.com/xiaosa.yjh/auto_insight
Author: xiaosa
Author-email: xiaosa.yjh@alibaba-inc.com
License: UNKNOWN
Platform: UNKNOWN
Classifier: Programming Language :: Python :: 3
Classifier: License :: OSI Approved :: MIT License
Classifier: Operating System :: OS Independent
Requires-Python: >=3.6
